{
  "appName": "WPS Office",
  "packageName": "cn.wps.moffice_eng",
  "category": "PRODUCTIVITY",
  "icon": "",
  "permissions": [
    "android.permission.ACCESS_FINE_LOCATION",
    "android.permission.ACCESS_NETWORK_STATE",
    "android.permission.ACCESS_WIFI_STATE",
    "android.permission.CAMERA",
    "android.permission.CHANGE_NETWORK_STATE",
    "android.permission.CHANGE_WIFI_STATE",
    "android.permission.GET_ACCOUNTS",
    "android.permission.INTERNET",
    "android.permission.NFC",
    "android.permission.READ_EXTERNAL_STORAGE",
    "android.permission.SYSTEM_ALERT_WINDOW",
    "android.permission.WAKE_LOCK",
    "android.permission.WRITE_EXTERNAL_STORAGE",
    "android.permission.WRITE_SYNC_SETTINGS",
    "cn.wps.moffice_eng.permission.C2D_MESSAGE",
    "cn.wps.moffice.permission.PermissionHandleActivity",
    "com.android.launcher.permission.INSTALL_SHORTCUT",
    "com.android.launcher.permission.UNINSTALL_SHORTCUT",
    "com.google.android.c2dm.permission.RECEIVE",
    "com.google.android.finsky.permission.BIND_GET_INSTALL_REFERRER_SERVICE",
    "com.google.android.providers.gsf.permission.READ_GSERVICES",
    "com.huawei.permission.HANDOFF",
    "com.huawei.permission.VASSIST_DESKTOP",
    "com.huawei.permission.VASSIST_DESKTOP_WPS",
    "com.permission.handle.activity.action"
  ],
  "version": "11.5.2",
  "trackers": [
    "Facebook Share",
    "Google DoubleClick",
    "Tencent Weiyun",
    "Inmobi",
    "Twitter MoPub",
    "Flurry",
    "AppsFlyer",
    "Google Firebase Analytics",
    "Facebook Login",
    "Tencent Stats",
    "Google Ads",
    "Facebook Ads"
  ]
}
