{
  "appName": "Tap-Tap Dance",
  "packageName": "com.waphoo.taptapdance",
  "category": "",
  "icon": "",
  "permissions": [
    "android.permission.ACCESS_NETWORK_STATE",
    "android.permission.ACCESS_WIFI_STATE",
    "android.permission.android.permission.READ_PHONE_STATE",
    "android.permission.INTERNET",
    "android.permission.READ_APP_BADGE",
    "android.permission.RECEIVE_BOOT_COMPLETED",
    "android.permission.VIBRATE",
    "android.permission.WAKE_LOCK",
    "android.permission.WRITE_EXTERNAL_STORAGE",
    "com.anddoes.launcher.permission.UPDATE_COUNT",
    "com.google.android.c2dm.permission.RECEIVE",
    "com.htc.launcher.permission.READ_SETTINGS",
    "com.htc.launcher.permission.UPDATE_SHORTCUT",
    "com.huawei.android.launcher.permission.CHANGE_BADGE",
    "com.huawei.android.launcher.permission.READ_SETTINGS",
    "com.huawei.android.launcher.permission.WRITE_SETTINGS",
    "com.majeur.launcher.permission.UPDATE_BADGE",
    "com.oppo.launcher.permission.READ_SETTINGS",
    "com.oppo.launcher.permission.WRITE_SETTINGS",
    "com.sec.android.provider.badge.permission.READ",
    "com.sec.android.provider.badge.permission.WRITE",
    "com.sonyericsson.home.permission.BROADCAST_BADGE",
    "com.sonymobile.home.permission.PROVIDER_INSERT_BADGE",
    "com.waphoo.taptapdance.permission.C2D_MESSAGE"
  ],
  "version": "1.3.4",
  "trackers": [
    "OneSignal",
    "ChartBoost"
  ],
  "network_connections": [
    {
      "package": "com.waphoo.taptapdance",
      "ptr_domain": "ec2-13-56-43-41.us-west-1.compute.amazonaws.com",
      "ip_address": "13.56.43.41",
      "loc_city": "San Jose",
      "loc_country": "United States",
      "loc_continent": "North America",
      "loc_long": "-121.891400",
      "loc_lat": "37.338800"
    },
    {
      "package": "com.waphoo.taptapdance",
      "ptr_domain": "vip0x055.map2.ssl.hwcdn.net",
      "ip_address": "209.197.3.85",
      "loc_city": "Phoenix",
      "loc_country": "United States",
      "loc_continent": "North America",
      "loc_long": "-112.067800",
      "loc_lat": "33.509700"
    },
    {
      "package": "com.waphoo.taptapdance",
      "ptr_domain": "N/A",
      "ip_address": "2400:cb00:2048:1::6810:cda5",
      "loc_city": "Columbus",
      "loc_country": "United States",
      "loc_continent": "North America",
      "loc_long": "-82.197100",
      "loc_lat": "35.253200"
    },
    {
      "package": "com.waphoo.taptapdance",
      "ptr_domain": "ec2-34-225-199-105.compute-1.amazonaws.com",
      "ip_address": "34.225.199.105",
      "loc_city": "Ashburn",
      "loc_country": "United States",
      "loc_continent": "North America",
      "loc_long": "-77.472800",
      "loc_lat": "39.048100"
    },
    {
      "package": "com.waphoo.taptapdance",
      "ptr_domain": "ec2-54-153-67-50.us-west-1.compute.amazonaws.com",
      "ip_address": "54.153.67.50",
      "loc_city": "San Jose",
      "loc_country": "United States",
      "loc_continent": "North America",
      "loc_long": "-121.891400",
      "loc_lat": "37.338800"
    },
    {
      "package": "com.waphoo.taptapdance",
      "ptr_domain": "server-54-230-143-168.sfo5.r.cloudfront.net",
      "ip_address": "54.230.143.168",
      "loc_city": "Seattle",
      "loc_country": "United States",
      "loc_continent": "North America",
      "loc_long": "-122.303200",
      "loc_lat": "47.540000"
    },
    {
      "package": "com.waphoo.taptapdance",
      "ptr_domain": "server-54-230-143-181.sfo5.r.cloudfront.net",
      "ip_address": "54.230.143.181",
      "loc_city": "Seattle",
      "loc_country": "United States",
      "loc_continent": "North America",
      "loc_long": "-122.303200",
      "loc_lat": "47.540000"
    },
    {
      "package": "com.waphoo.taptapdance",
      "ptr_domain": "server-54-230-143-208.sfo5.r.cloudfront.net",
      "ip_address": "54.230.143.208",
      "loc_city": "Seattle",
      "loc_country": "United States",
      "loc_continent": "North America",
      "loc_long": "-122.303200",
      "loc_lat": "47.540000"
    }
  ]
}
