{
  "appName": "Seecrypt",
  "packageName": "com.seecrypt.sc3",
  "category": "COMMUNICATION",
  "icon": "",
  "permissions": [
    "android.permission.ACCESS_NETWORK_STATE",
    "android.permission.ACCESS_WIFI_STATE",
    "android.permission.BLUETOOTH",
    "android.permission.BLUETOOTH_ADMIN",
    "android.permission.BROADCAST_STICKY",
    "android.permission.INTERNET",
    "android.permission.MODIFY_AUDIO_SETTINGS",
    "android.permission.RECEIVE_BOOT_COMPLETED",
    "android.permission.VIBRATE",
    "android.permission.WAKE_LOCK",
    "android.permission.READ_PHONE_STATE",
    "android.permission.CAMERA",
    "android.permission.RECORD_AUDIO",
    "android.permission.READ_EXTERNAL_STORAGE",
    "android.permission.WRITE_EXTERNAL_STORAGE",
    "android.permission.READ_CONTACTS",
    "android.permission.GET_ACCOUNTS",
    "android.permission.DOWNLOAD_WITHOUT_NOTIFICATION",
    "android.permission.MANAGE_DOCUMENTS",
    "android.permission.READ_PROFILE",
    "com.google.android.c2dm.permission.RECEIVE",
    "android.permission.REQUEST_IGNORE_BATTERY_OPTIMIZATIONS",
    "com.seecrypt.sc3.permission.C2D_MESSAGE",
    "com.seecrypt.sc3.permission.C2D_MESSAGE",
    "com.google.android.finsky.permission.BIND_GET_INSTALL_REFERRER_SERVICE",
    "com.sec.android.provider.badge.permission.READ",
    "com.sec.android.provider.badge.permission.WRITE",
    "com.htc.launcher.permission.READ_SETTINGS",
    "com.htc.launcher.permission.UPDATE_SHORTCUT",
    "com.sonyericsson.home.permission.BROADCAST_BADGE",
    "com.anddoes.launcher.permission.UPDATE_COUNT",
    "com.majeur.launcher.permission.UPDATE_BADGE"
  ],
  "version": "3.77.2.539",
  "trackers": [
    "HockeyApp",
    "Google Firebase Analytics"
  ],
  "network_connections": [
    {
      "package": "com.seecrypt.sc3",
      "ptr_domain": "N/A",
      "ip_address": "197.215.228.128",
      "loc_city": "N/A",
      "loc_country": "South Africa",
      "loc_continent": "Africa",
      "loc_long": "24.000000",
      "loc_lat": "-29.000000"
    },
    {
      "package": "com.seecrypt.sc3",
      "ptr_domain": "N/A",
      "ip_address": "197.215.228.129",
      "loc_city": "N/A",
      "loc_country": "South Africa",
      "loc_continent": "Africa",
      "loc_long": "24.000000",
      "loc_lat": "-29.000000"
    }
  ]
}
