{
  "appName": "Chewy",
  "packageName": "com.chewy.android",
  "category": "SHOPPING",
  "icon": "",
  "permissions": [
    "android.permission.ACCESS_NETWORK_STATE",
    "android.permission.ACCESS_WIFI_STATE",
    "android.permission.CAMERA",
    "android.permission.INTERNET",
    "android.permission.READ_EXTERNAL_STORAGE",
    "android.permission.REORDER_TASKS",
    "android.permission.VIBRATE",
    "android.permission.WAKE_LOCK",
    "android.permission.WRITE_EXTERNAL_STORAGE",
    "com.google.android.c2dm.permission.RECEIVE",
    "com.google.android.finsky.permission.BIND_GET_INSTALL_REFERRER_SERVICE",
    "com.google.android.providers.gsf.permission.READ_GSERVICES"
  ],
  "version": "2.11.1",
  "trackers": [
    "Google Firebase Analytics",
    "Google CrashLytics",
    "Braze (formerly Appboy)",
    "Branch",
    "MParticle",
    "AppsFlyer"
  ]
}
