{
  "appName": "Asana Rebel",
  "packageName": "com.asanayoga.asanarebel",
  "category": "HEALTH_AND_FITNESS",
  "icon": "",
  "permissions": [
    "android.permission.ACCESS_NETWORK_STATE",
    "android.permission.ACCESS_WIFI_STATE",
    "android.permission.FOREGROUND_SERVICE",
    "android.permission.INTERNET",
    "android.permission.READ_EXTERNAL_STORAGE",
    "android.permission.WAKE_LOCK",
    "android.permission.WRITE_EXTERNAL_STORAGE",
    "com.google.android.c2dm.permission.RECEIVE",
    "com.google.android.finsky.permission.BIND_GET_INSTALL_REFERRER_SERVICE",
    "com.google.android.providers.gsf.permission.READ_GSERVICES"
  ],
  "version": "3.0.4.1700",
  "trackers": [
    "Google Analytics",
    "Facebook Analytics",
    "Snowplow",
    "Facebook Share",
    "Facebook Login",
    "Facebook Places",
    "Google CrashLytics",
    "Adjust",
    "Amplitude",
    "Google Firebase Analytics",
    "Braze (formerly Appboy)"
  ]
}
