{
  "appName": "Fitbit Coach",
  "packageName": "com.fitstar.pt",
  "category": "HEALTH_AND_FITNESS",
  "icon": "",
  "permissions": [
    "android.permission.ACCESS_NETWORK_STATE",
    "android.permission.ACCESS_WIFI_STATE",
    "android.permission.INTERNET",
    "android.permission.MEDIA_CONTENT_CONTROL",
    "android.permission.NFC",
    "android.permission.READ_PHONE_STATE",
    "android.permission.WAKE_LOCK",
    "android.permission.WRITE_EXTERNAL_STORAGE",
    "com.fitbit.FitbitMobile.permission.SSO",
    "com.fitstar.pt.permission.C2D_MESSAGE",
    "com.google.android.c2dm.permission.RECEIVE"
  ],
  "version": "4.4.1",
  "trackers": [
    "Google CrashLytics",
    "Facebook Share",
    "Google Analytics",
    "Google Firebase Analytics",
    "Facebook Analytics",
    "Facebook Login"
  ],
  "network_connections": [
    {
      "package": "com.fitstar.pt",
      "ptr_domain": "148.254.178.107.bc.googleusercontent.com",
      "ip_address": "107.178.254.148",
      "loc_city": "N/A",
      "loc_country": "United States",
      "loc_continent": "North America",
      "loc_long": "-77.248100",
      "loc_lat": "38.658300"
    },
    {
      "package": "com.fitstar.pt",
      "ptr_domain": "ec2-107-22-241-65.compute-1.amazonaws.com",
      "ip_address": "107.22.241.65",
      "loc_city": "Ashburn",
      "loc_country": "United States",
      "loc_continent": "North America",
      "loc_long": "-77.472800",
      "loc_lat": "39.048100"
    },
    {
      "package": "com.fitstar.pt",
      "ptr_domain": "edge-star-shv-02-sin6.facebook.com",
      "ip_address": "157.240.13.14",
      "loc_city": "N/A",
      "loc_country": "United States",
      "loc_continent": "North America",
      "loc_long": "-97.822000",
      "loc_lat": "37.751000"
    },
    {
      "package": "com.fitstar.pt",
      "ptr_domain": "edge-star6-shv-02-sin6.facebook.com",
      "ip_address": "2a03:2880:f00c:20d:face:b00c:0:2",
      "loc_city": "N/A",
      "loc_country": "Ireland",
      "loc_continent": "Europe",
      "loc_long": "-8.000000",
      "loc_lat": "53.000000"
    },
    {
      "package": "com.fitstar.pt",
      "ptr_domain": "N/A",
      "ip_address": "2a03:2880:f026:13:face:b00c:0:2",
      "loc_city": "N/A",
      "loc_country": "Ireland",
      "loc_continent": "Europe",
      "loc_long": "-8.000000",
      "loc_lat": "53.000000"
    },
    {
      "package": "com.fitstar.pt",
      "ptr_domain": "ec2-35-162-236-90.us-west-2.compute.amazonaws.com",
      "ip_address": "35.162.236.90",
      "loc_city": "Boardman",
      "loc_country": "United States",
      "loc_continent": "North America",
      "loc_long": "-119.714300",
      "loc_lat": "45.849100"
    },
    {
      "package": "com.fitstar.pt",
      "ptr_domain": "ec2-52-34-169-71.us-west-2.compute.amazonaws.com",
      "ip_address": "52.34.169.71",
      "loc_city": "Boardman",
      "loc_country": "United States",
      "loc_continent": "North America",
      "loc_long": "-119.714300",
      "loc_lat": "45.849100"
    },
    {
      "package": "com.fitstar.pt",
      "ptr_domain": "ec2-54-243-133-174.compute-1.amazonaws.com",
      "ip_address": "54.243.133.174",
      "loc_city": "Ashburn",
      "loc_country": "United States",
      "loc_continent": "North America",
      "loc_long": "-77.472800",
      "loc_lat": "39.048100"
    },
    {
      "package": "com.fitstar.pt",
      "ptr_domain": "ec2-54-243-149-90.compute-1.amazonaws.com",
      "ip_address": "54.243.149.90",
      "loc_city": "Ashburn",
      "loc_country": "United States",
      "loc_continent": "North America",
      "loc_long": "-77.472800",
      "loc_lat": "39.048100"
    },
    {
      "package": "com.fitstar.pt",
      "ptr_domain": "ec2-54-243-93-187.compute-1.amazonaws.com",
      "ip_address": "54.243.93.187",
      "loc_city": "Ashburn",
      "loc_country": "United States",
      "loc_continent": "North America",
      "loc_long": "-77.472800",
      "loc_lat": "39.048100"
    }
  ]
}
