{
  "appName": "Tower With Friends",
  "packageName": "com.metafun.tower",
  "category": "",
  "icon": "",
  "permissions": [
    "android.permission.ACCESS_NETWORK_STATE",
    "android.permission.ACCESS_WIFI_STATE",
    "android.permission.INTERNET",
    "android.permission.READ_EXTERNAL_STORAGE",
    "android.permission.READ_PHONE_STATE",
    "android.permission.WRITE_EXTERNAL_STORAGE"
  ],
  "version": "3.5.3029",
  "trackers": [
    "AdColony",
    "Google DoubleClick",
    "Heyzap (bought by Fyber)",
    "Adjust",
    "Unity3d Ads",
    "AppLovin",
    "Flurry",
    "Duapps",
    "Umeng Analytics",
    "Google Ads",
    "Facebook Ads",
    "Appnext",
    "Inmobi",
    "Vungle",
    "ironSource"
  ],
  "network_connections": [
    {
      "package": "com.metafun.tower",
      "ptr_domain": "ec2-184-73-137-123.compute-1.amazonaws.com",
      "ip_address": "184.73.137.123",
      "loc_city": "Ashburn",
      "loc_country": "United States",
      "loc_continent": "North America",
      "loc_long": "-77.472800",
      "loc_lat": "39.048100"
    },
    {
      "package": "com.metafun.tower",
      "ptr_domain": "a23-203-229-5.deploy.static.akamaitechnologies.com",
      "ip_address": "23.203.229.5",
      "loc_city": "N/A",
      "loc_country": "United States",
      "loc_continent": "North America",
      "loc_long": "-97.822000",
      "loc_lat": "37.751000"
    },
    {
      "package": "com.metafun.tower",
      "ptr_domain": "nuq04s29-in-x02.1e100.net",
      "ip_address": "2607:f8b0:4005:801::2002",
      "loc_city": "N/A",
      "loc_country": "United States",
      "loc_continent": "North America",
      "loc_long": "-97.822000",
      "loc_lat": "37.751000"
    },
    {
      "package": "com.metafun.tower",
      "ptr_domain": "sfo03s01-in-x01.1e100.net",
      "ip_address": "2607:f8b0:4005:805::2001",
      "loc_city": "N/A",
      "loc_country": "United States",
      "loc_continent": "North America",
      "loc_long": "-97.822000",
      "loc_lat": "37.751000"
    },
    {
      "package": "com.metafun.tower",
      "ptr_domain": "sfo03s01-in-x0a.1e100.net",
      "ip_address": "2607:f8b0:4005:805::200a",
      "loc_city": "N/A",
      "loc_country": "United States",
      "loc_continent": "North America",
      "loc_long": "-97.822000",
      "loc_lat": "37.751000"
    },
    {
      "package": "com.metafun.tower",
      "ptr_domain": "N/A",
      "ip_address": "2607:f8b0:4005:c::8",
      "loc_city": "N/A",
      "loc_country": "United States",
      "loc_continent": "North America",
      "loc_long": "-97.822000",
      "loc_lat": "37.751000"
    },
    {
      "package": "com.metafun.tower",
      "ptr_domain": "edge-star6-shv-01-iad3.facebook.com",
      "ip_address": "2a03:2880:f003:c07:face:b00c:0:2",
      "loc_city": "N/A",
      "loc_country": "Ireland",
      "loc_continent": "Europe",
      "loc_long": "-8.000000",
      "loc_lat": "53.000000"
    },
    {
      "package": "com.metafun.tower",
      "ptr_domain": "N/A",
      "ip_address": "2a03:2880:f022:6:face:b00c:0:2",
      "loc_city": "N/A",
      "loc_country": "Ireland",
      "loc_continent": "Europe",
      "loc_long": "-8.000000",
      "loc_lat": "53.000000"
    },
    {
      "package": "com.metafun.tower",
      "ptr_domain": "edge-z-m-mini6-shv-02-lax3.facebook.com",
      "ip_address": "2a03:2880:f10d:184:face:b00c:0:14c9",
      "loc_city": "N/A",
      "loc_country": "Ireland",
      "loc_continent": "Europe",
      "loc_long": "-8.000000",
      "loc_lat": "53.000000"
    }
  ]
}
