{
  "appName": "Jurassic World",
  "packageName": "com.ludia.jurassicworld",
  "category": "GAME_SIMULATION",
  "icon": "",
  "permissions": [
    "android.permission.ACCESS_NETWORK_STATE",
    "android.permission.ACCESS_WIFI_STATE",
    "android.permission.CAMERA",
    "android.permission.INTERNET",
    "android.permission.RECEIVE_BOOT_COMPLETED",
    "android.permission.REQUEST_INSTALL_PACKAGES",
    "android.permission.VIBRATE",
    "android.permission.WAKE_LOCK",
    "android.permission.WRITE_EXTERNAL_STORAGE",
    "com.google.android.c2dm.permission.RECEIVE",
    "com.google.android.finsky.permission.BIND_GET_INSTALL_REFERRER_SERVICE"
  ],
  "version": "1.33.2",
  "trackers": [
    "Facebook Places",
    "Google Ads",
    "Google Firebase Analytics",
    "Urbanairship",
    "Facebook Login",
    "Tapjoy",
    "Facebook Ads",
    "Amplitude",
    "Google DoubleClick",
    "AppLovin",
    "Adjust",
    "Facebook Analytics",
    "ChartBoost",
    "Facebook Share",
    "HelpShift",
    "Moat",
    "HockeyApp"
  ]
}
