{
  "appName": "myVEGAS",
  "packageName": "com.playstudios.myvegas.blackjack",
  "category": "GAME_CASINO",
  "icon": "",
  "permissions": [
    "android.permission.ACCESS_FINE_LOCATION",
    "android.permission.ACCESS_NETWORK_STATE",
    "android.permission.ACCESS_WIFI_STATE",
    "android.permission.GET_ACCOUNTS",
    "android.permission.INTERNET",
    "android.permission.READ_EXTERNAL_STORAGE",
    "android.permission.READ_PHONE_STATE",
    "android.permission.VIBRATE",
    "android.permission.WAKE_LOCK",
    "android.permission.WRITE_EXTERNAL_STORAGE",
    "com.google.android.c2dm.permission.RECEIVE",
    "com.google.android.finsky.permission.BIND_GET_INSTALL_REFERRER_SERVICE",
    "com.playstudios.myvegas.blackjack.permission.C2D_MESSAGE"
  ],
  "version": "1.22.1",
  "trackers": [
    "Google DoubleClick",
    "Facebook Login",
    "ironSource",
    "Facebook Share",
    "Adjust",
    "Facebook Places",
    "Facebook Ads",
    "Facebook Analytics",
    "Google CrashLytics",
    "Twitter MoPub",
    "Moat",
    "HelpShift",
    "Google Ads",
    "Unity3d Ads",
    "AdColony"
  ]
}
