{
  "appName": "Clubcard",
  "packageName": "com.tesco.clubcardmobile",
  "category": "",
  "icon": "",
  "permissions": [
    "android.permission.ACCESS_COARSE_LOCATION",
    "android.permission.ACCESS_FINE_LOCATION",
    "android.permission.ACCESS_NETWORK_STATE",
    "android.permission.ACCESS_WIFI_STATE",
    "android.permission.CAMERA",
    "android.permission.GET_TASKS",
    "android.permission.INTERNET",
    "android.permission.READ_EXTERNAL_STORAGE",
    "android.permission.RECEIVE_BOOT_COMPLETED",
    "android.permission.USE_FINGERPRINT",
    "android.permission.WAKE_LOCK",
    "android.permission.WRITE_EXTERNAL_STORAGE",
    "android.permission.WRITE_SETTINGS",
    "com.google.android.c2dm.permission.RECEIVE",
    "com.google.android.finsky.permission.BIND_GET_INSTALL_REFERRER_SERVICE",
    "com.google.android.providers.gsf.permission.READ_GSERVICES",
    "com.tesco.clubcardmobile.permission.C2D_MESSAGE",
    "com.tesco.clubcardmobile.permission.MAPS_RECEIVE"
  ],
  "version": "6.2",
  "trackers": [
    "Google DoubleClick",
    "LeanPlum",
    "Omniture",
    "Google Ads",
    "Appdynamics",
    "Demdex"
  ],
  "network_connections": [
    {
      "package": "com.tesco.clubcardmobile",
      "ptr_domain": "ec2-34-249-151-77.eu-west-1.compute.amazonaws.com",
      "ip_address": "34.249.151.77",
      "loc_city": "Dublin",
      "loc_country": "Ireland",
      "loc_continent": "Europe",
      "loc_long": "-6.248800",
      "loc_lat": "53.333800"
    },
    {
      "package": "com.tesco.clubcardmobile",
      "ptr_domain": "ec2-52-31-18-86.eu-west-1.compute.amazonaws.com",
      "ip_address": "52.31.18.86",
      "loc_city": "Dublin",
      "loc_country": "Ireland",
      "loc_continent": "Europe",
      "loc_long": "-6.248800",
      "loc_lat": "53.333800"
    },
    {
      "package": "com.tesco.clubcardmobile",
      "ptr_domain": "ec2-52-7-193-50.compute-1.amazonaws.com",
      "ip_address": "52.7.193.50",
      "loc_city": "Ashburn",
      "loc_country": "United States",
      "loc_continent": "North America",
      "loc_long": "-77.472800",
      "loc_lat": "39.048100"
    },
    {
      "package": "com.tesco.clubcardmobile",
      "ptr_domain": "server-52-85-74-108.lhr3.r.cloudfront.net",
      "ip_address": "52.85.74.108",
      "loc_city": "Seattle",
      "loc_country": "United States",
      "loc_continent": "North America",
      "loc_long": "-122.345100",
      "loc_lat": "47.634800"
    }
  ]
}
