{
  "appName": "KidloLand",
  "packageName": "com.internetdesignzone.nurseryrhymes",
  "category": "",
  "icon": "",
  "permissions": [
    "android.permission.ACCESS_NETWORK_STATE",
    "android.permission.CAMERA",
    "android.permission.DISABLE_KEYGUARD",
    "android.permission.INTERNET",
    "android.permission.READ_PHONE_STATE",
    "android.permission.VIBRATE",
    "android.permission.WAKE_LOCK",
    "android.permission.WRITE_EXTERNAL_STORAGE"
  ],
  "version": "11.7",
  "trackers": [
    "Flurry",
    "Google Analytics",
    "Google Firebase Analytics"
  ],
  "network_connections": [
    {
      "package": "com.internetdesignzone.nurseryrhymes",
      "ptr_domain": "a104-68-101-25.deploy.static.akamaitechnologies.com",
      "ip_address": "104.68.101.25",
      "loc_city": "N/A",
      "loc_country": "United States",
      "loc_continent": "North America",
      "loc_long": "-97.822000",
      "loc_lat": "37.751000"
    },
    {
      "package": "com.internetdesignzone.nurseryrhymes",
      "ptr_domain": "N/A",
      "ip_address": "2001:4998:c:292f::3001",
      "loc_city": "N/A",
      "loc_country": "United States",
      "loc_continent": "North America",
      "loc_long": "-97.822000",
      "loc_lat": "37.751000"
    },
    {
      "package": "com.internetdesignzone.nurseryrhymes",
      "ptr_domain": "a23-197-98-136.deploy.static.akamaitechnologies.com",
      "ip_address": "23.197.98.136",
      "loc_city": "N/A",
      "loc_country": "United States",
      "loc_continent": "North America",
      "loc_long": "-97.822000",
      "loc_lat": "37.751000"
    },
    {
      "package": "com.internetdesignzone.nurseryrhymes",
      "ptr_domain": "a23-45-86-146.deploy.static.akamaitechnologies.com",
      "ip_address": "23.45.86.146",
      "loc_city": "N/A",
      "loc_country": "United States",
      "loc_continent": "North America",
      "loc_long": "-97.822000",
      "loc_lat": "37.751000"
    },
    {
      "package": "com.internetdesignzone.nurseryrhymes",
      "ptr_domain": "edge-star6-shv-02-ort2.facebook.com",
      "ip_address": "2a03:2880:f027:20e:face:b00c:0:2",
      "loc_city": "N/A",
      "loc_country": "Ireland",
      "loc_continent": "Europe",
      "loc_long": "-8.000000",
      "loc_lat": "53.000000"
    },
    {
      "package": "com.internetdesignzone.nurseryrhymes",
      "ptr_domain": "UNKNOWN-74-6-34-X.yahoo.com",
      "ip_address": "74.6.34.123",
      "loc_city": "N/A",
      "loc_country": "United States",
      "loc_continent": "North America",
      "loc_long": "-97.822000",
      "loc_lat": "37.751000"
    }
  ]
}
