{
  "appName": "",
  "packageName": "com.pixelus.dashclock.ext.mystorage",
  "category": "TOOLS",
  "icon": "",
  "permissions": [
    "android.permission.INTERNET"
  ],
  "version": "1.4.11",
  "trackers": [],
  "network_connections": [
    {
      "package": "com.pixelus.dashclock.ext.mystorage",
      "ptr_domain": "ec2-184-73-208-78.compute-1.amazonaws.com",
      "ip_address": "184.73.208.78",
      "loc_city": "Ashburn",
      "loc_country": "United States",
      "loc_continent": "North America",
      "loc_long": "-77.472800",
      "loc_lat": "39.048100"
    },
    {
      "package": "com.pixelus.dashclock.ext.mystorage",
      "ptr_domain": "ec2-23-23-235-188.compute-1.amazonaws.com",
      "ip_address": "23.23.235.188",
      "loc_city": "Ashburn",
      "loc_country": "United States",
      "loc_continent": "North America",
      "loc_long": "-77.472800",
      "loc_lat": "39.048100"
    },
    {
      "package": "com.pixelus.dashclock.ext.mystorage",
      "ptr_domain": "ec2-23-23-84-194.compute-1.amazonaws.com",
      "ip_address": "23.23.84.194",
      "loc_city": "Ashburn",
      "loc_country": "United States",
      "loc_continent": "North America",
      "loc_long": "-77.472800",
      "loc_lat": "39.048100"
    }
  ]
}
