{
  "appName": "Nozbe",
  "packageName": "com.nozbe.mobile",
  "category": "",
  "icon": "",
  "permissions": [
    "android.permission.ACCESS_NETWORK_STATE",
    "android.permission.CAMERA",
    "android.permission.CAMERA2",
    "android.permission.INTERNET",
    "android.permission.MODIFY_AUDIO_SETTINGS",
    "android.permission.READ_APP_BADGE",
    "android.permission.READ_EXTERNAL_STORAGE",
    "android.permission.READ_PHONE_STATE",
    "android.permission.RECORD_AUDIO",
    "android.permission.RECORD_VIDEO",
    "android.permission.VIBRATE",
    "android.permission.WAKE_LOCK",
    "android.permission.WRITE_EXTERNAL_STORAGE",
    "com.anddoes.launcher.permission.UPDATE_COUNT",
    "com.google.android.c2dm.permission.RECEIVE",
    "com.google.android.finsky.permission.BIND_GET_INSTALL_REFERRER_SERVICE",
    "com.htc.launcher.permission.READ_SETTINGS",
    "com.htc.launcher.permission.UPDATE_SHORTCUT",
    "com.huawei.android.launcher.permission.CHANGE_BADGE",
    "com.huawei.android.launcher.permission.READ_SETTINGS",
    "com.huawei.android.launcher.permission.WRITE_SETTINGS",
    "com.majeur.launcher.permission.UPDATE_BADGE",
    "com.nozbe.mobile.permission.C2D_MESSAGE",
    "com.oppo.launcher.permission.READ_SETTINGS",
    "com.oppo.launcher.permission.WRITE_SETTINGS",
    "com.sec.android.provider.badge.permission.READ",
    "com.sec.android.provider.badge.permission.WRITE",
    "com.sonyericsson.home.permission.BROADCAST_BADGE",
    "com.sonymobile.home.permission.PROVIDER_INSERT_BADGE",
    "me.everything.badger.permission.BADGE_COUNT_READ",
    "me.everything.badger.permission.BADGE_COUNT_WRITE"
  ],
  "version": "3.10",
  "trackers": [
    "Google CrashLytics",
    "Google Firebase Analytics"
  ],
  "network_connections": [
    {
      "package": "com.nozbe.mobile",
      "ptr_domain": "ec2-52-16-173-74.eu-west-1.compute.amazonaws.com",
      "ip_address": "52.16.173.74",
      "loc_city": "Dublin",
      "loc_country": "Ireland",
      "loc_continent": "Europe",
      "loc_long": "-6.248800",
      "loc_lat": "53.333800"
    },
    {
      "package": "com.nozbe.mobile",
      "ptr_domain": "static.85-10-232-84.clients.your-server.de",
      "ip_address": "85.10.232.84",
      "loc_city": "N/A",
      "loc_country": "Germany",
      "loc_continent": "Europe",
      "loc_long": "9.491000",
      "loc_lat": "51.299300"
    }
  ]
}
