{
  "appName": "Internet Speed Monitor",
  "packageName": "com.andcreate.app.internetspeedmonitor",
  "category": "TOOLS",
  "icon": "",
  "permissions": [
    "android.permission.ACCESS_COARSE_LOCATION",
    "android.permission.ACCESS_NETWORK_STATE",
    "android.permission.ACCESS_WIFI_STATE",
    "android.permission.FOREGROUND_SERVICE",
    "android.permission.INTERNET",
    "android.permission.PACKAGE_USAGE_STATS",
    "android.permission.READ_PHONE_STATE",
    "android.permission.RECEIVE_BOOT_COMPLETED",
    "android.permission.SYSTEM_ALERT_WINDOW",
    "android.permission.WAKE_LOCK",
    "com.google.android.c2dm.permission.RECEIVE",
    "com.google.android.finsky.permission.BIND_GET_INSTALL_REFERRER_SERVICE"
  ],
  "version": "0.9.3.1",
  "trackers": [
    "Google Firebase Analytics",
    "Google Ads",
    "Google CrashLytics"
  ],
  "network_connections": [
    {
      "package": "com.andcreate.app.internetspeedmonitor",
      "ptr_domain": "ec2-50-17-228-124.compute-1.amazonaws.com",
      "ip_address": "50.17.228.124",
      "loc_city": "Ashburn",
      "loc_country": "United States",
      "loc_continent": "North America",
      "loc_long": "-77.472800",
      "loc_lat": "39.048100"
    }
  ]
}
