{
  "appName": "Simplii",
  "packageName": "com.pcfinancial.mobile",
  "category": "FINANCE",
  "icon": "",
  "permissions": [
    "android.permission.ACCESS_COARSE_LOCATION",
    "android.permission.ACCESS_FINE_LOCATION",
    "android.permission.ACCESS_NETWORK_STATE",
    "android.permission.CAMERA",
    "android.permission.FOREGROUND_SERVICE",
    "android.permission.INTERNET",
    "android.permission.READ_CONTACTS",
    "android.permission.USE_FINGERPRINT",
    "android.permission.VIBRATE",
    "android.permission.WAKE_LOCK",
    "android.permission.WRITE_CONTACTS",
    "android.permission.WRITE_EXTERNAL_STORAGE",
    "com.google.android.c2dm.permission.RECEIVE",
    "com.google.android.providers.gsf.permission.READ_GSERVICES",
    "com.pcfinancial.mobile.permission.C2D_MESSAGE",
    ".permission.MAPS_RECIEVE"
  ],
  "version": "7.8.3",
  "trackers": [
    "Google Firebase Analytics",
    "Facebook Analytics",
    "Braze (formerly Appboy)",
    "Facebook Share",
    "Facebook Login",
    "Google Analytics"
  ],
  "network_connections": [
    {
      "package": "com.pcfinancial.mobile",
      "ptr_domain": "N/A",
      "ip_address": "151.101.125.130",
      "loc_city": "Toronto",
      "loc_country": "Canada",
      "loc_continent": "North America",
      "loc_long": "-79.419500",
      "loc_lat": "43.664400"
    },
    {
      "package": "com.pcfinancial.mobile",
      "ptr_domain": "a23-49-83-143.deploy.static.akamaitechnologies.com",
      "ip_address": "23.49.83.143",
      "loc_city": "N/A",
      "loc_country": "United States",
      "loc_continent": "North America",
      "loc_long": "-97.822000",
      "loc_lat": "37.751000"
    },
    {
      "package": "com.pcfinancial.mobile",
      "ptr_domain": "N/A",
      "ip_address": "63.140.33.17",
      "loc_city": "N/A",
      "loc_country": "United States",
      "loc_continent": "North America",
      "loc_long": "-97.822000",
      "loc_lat": "37.751000"
    }
  ]
}
