{
  "appName": "Simple Workout Log",
  "packageName": "com.selahsoft.workoutlog",
  "category": "",
  "icon": "",
  "permissions": [
    "android.permission.ACCESS_NETWORK_STATE",
    "android.permission.INTERNET",
    "android.permission.VIBRATE",
    "android.permission.WAKE_LOCK",
    "android.permission.WRITE_EXTERNAL_STORAGE"
  ],
  "version": "3.8.5",
  "trackers": [
    "Google DoubleClick",
    "Google Analytics",
    "Google Ads"
  ],
  "network_connections": [
    {
      "package": "com.selahsoft.workoutlog",
      "ptr_domain": "iad23s44-in-f162.1e100.net",
      "ip_address": "216.58.217.162",
      "loc_city": "Bluffdale",
      "loc_country": "United States",
      "loc_continent": "North America",
      "loc_long": "-111.943900",
      "loc_lat": "40.495300"
    },
    {
      "package": "com.selahsoft.workoutlog",
      "ptr_domain": "iad23s41-in-f1.1e100.net",
      "ip_address": "216.58.217.65",
      "loc_city": "Bluffdale",
      "loc_country": "United States",
      "loc_continent": "North America",
      "loc_long": "-111.943900",
      "loc_lat": "40.495300"
    }
  ]
}
