{
  "appName": "Le Figaro",
  "packageName": "fr.playsoft.lefigarov3",
  "category": "NEWS_AND_MAGAZINES",
  "icon": "",
  "permissions": [
    "android.permission.ACCESS_NETWORK_STATE",
    "android.permission.ACCESS_WIFI_STATE",
    "android.permission.INTERNET",
    "android.permission.RECEIVE_BOOT_COMPLETED",
    "android.permission.VIBRATE",
    "android.permission.WAKE_LOCK",
    "android.permission.WRITE_EXTERNAL_STORAGE",
    "com.google.android.c2dm.permission.RECEIVE",
    "com.google.android.finsky.permission.BIND_GET_INSTALL_REFERRER_SERVICE"
  ],
  "version": "5.1.11",
  "trackers": [
    "Widespace",
    "Inmobi",
    "Flurry",
    "Adjust",
    "Amazon Advertisement",
    "Taboola",
    "AppNexus",
    "Twitter MoPub",
    "Smart",
    "Google Firebase Analytics",
    "Google DoubleClick",
    "Google Analytics",
    "Google Ads",
    "Google CrashLytics",
    "Krux",
    "Facebook Ads"
  ]
}
