{
  "appName": "ΣΚΑΙ.gr",
  "packageName": "gr.skai.skai_android",
  "category": "ENTERTAINMENT",
  "icon": "",
  "permissions": [
    "android.permission.ACCESS_COARSE_LOCATION",
    "android.permission.ACCESS_FINE_LOCATION",
    "android.permission.ACCESS_NETWORK_STATE",
    "android.permission.ACCESS_WIFI_STATE",
    "android.permission.INTERNET",
    "android.permission.MODIFY_AUDIO_SETTINGS",
    "android.permission.VIBRATE",
    "android.permission.WAKE_LOCK",
    "com.google.android.c2dm.permission.RECEIVE",
    "gr.skai.skai_android.permission.C2D_MESSAGE"
  ],
  "version": "5.8",
  "trackers": [
    "Google DoubleClick",
    "Google Ads",
    "Google Firebase Analytics",
    "Google Analytics",
    "OneSignal",
    "OutBrain"
  ],
  "network_connections": [
    {
      "package": "gr.skai.skai_android",
      "ptr_domain": "ec2-35-156-222-240.eu-central-1.compute.amazonaws.com",
      "ip_address": "35.156.222.240",
      "loc_city": "Frankfurt am Main",
      "loc_country": "Germany",
      "loc_continent": "Europe",
      "loc_long": "8.684200",
      "loc_lat": "50.115500"
    },
    {
      "package": "gr.skai.skai_android",
      "ptr_domain": "ec2-35-157-37-23.eu-central-1.compute.amazonaws.com",
      "ip_address": "35.157.37.23",
      "loc_city": "Frankfurt am Main",
      "loc_country": "Germany",
      "loc_continent": "Europe",
      "loc_long": "8.684200",
      "loc_lat": "50.115500"
    }
  ]
}
