{
  "appName": "FileStream.Me Client",
  "packageName": "me.filestream.client",
  "category": "ENTERTAINMENT",
  "icon": "",
  "permissions": [
    "android.permission.ACCESS_NETWORK_STATE",
    "android.permission.FOREGROUND_SERVICE",
    "android.permission.GET_TASKS",
    "android.permission.INTERNET",
    "android.permission.READ_EXTERNAL_STORAGE",
    "android.permission.WAKE_LOCK",
    "android.permission.WRITE_EXTERNAL_STORAGE",
    "com.sony.mobile.permission.SYSTEM_UI_VISIBILITY_EXTENSION"
  ],
  "version": "2.5.0",
  "trackers": [
    "Google Firebase Analytics",
    "Facebook Share",
    "Facebook Login",
    "Google Analytics",
    "Facebook Analytics"
  ]
}
